fifo_sync.v
module fifo_sync #(
    parameter fifo_depth = 8,
    parameter data_width = 16
)(
    input clk,
    input rst_n,
    input cs,
    input rd_en,
    input wr_en,
    input [data_width-1:0] d_in,
    output reg [data_width-1:0] d_out,
    output empty,
    output full
);

localparam pointer_width = $clog2(fifo_depth);

reg [data_width-1:0] fifo [fifo_depth-1:0];

reg [pointer_width:0] wr_ptr;
reg [pointer_width:0] rd_ptr;


// WRITE
always @(posedge clk or negedge rst_n) begin
    if (!rst_n)
        wr_ptr <= 0;
    else if (cs && wr_en && !full) begin
        fifo[wr_ptr[pointer_width-1:0]] <= d_in;
        wr_ptr <= wr_ptr + 1'b1;
    end
end


// READ
always @(posedge clk or negedge rst_n) begin
    if (!rst_n)
        rd_ptr <= 0;
    else if (cs && rd_en && !empty) begin
        d_out <= fifo[rd_ptr[pointer_width-1:0]];
        rd_ptr <= rd_ptr + 1'b1;
    end
end


// STATUS
assign empty = (wr_ptr == rd_ptr);

assign full = (wr_ptr == {
    ~rd_ptr[pointer_width],
    rd_ptr[pointer_width-1:0]
});

endmodule

fifo_sync_tb.v
`timescale 1ns/1ps

module fifo_sync_tb;

    parameter fifo_depth = 8;
    parameter data_width = 16;

    reg clk;
    reg rst_n;
    reg cs;
    reg rd_en;
    reg wr_en;
    reg [data_width-1:0] d_in;

    wire [data_width-1:0] d_out;
    wire empty;
    wire full;

    reg all_pass;
    reg test_pass;


    // DUT
    fifo_sync #(
        .fifo_depth(fifo_depth),
        .data_width(data_width)
    ) dut (
        .clk(clk),
        .rst_n(rst_n),
        .cs(cs),
        .rd_en(rd_en),
        .wr_en(wr_en),
        .d_in(d_in),
        .d_out(d_out),
        .empty(empty),
        .full(full)
    );
  // VCD waveform generation
    initial begin
        $dumpfile("fifo_sync.vcd");
        $dumpvars(0, fifo_sync_tb);
    end


    // Clock generation
    initial begin
        clk = 0;
        forever #5 clk = ~clk;
    end


    // Test sequence
    initial begin

        all_pass = 1'b1;
        test_pass = 1'b1;

        rst_n = 0;
        cs    = 0;
        rd_en = 0;
        wr_en = 0;
        d_in  = 0;


        // TEST 1: RESET

        #12;

        rst_n = 1;
        cs = 1;

        #10;

        if (empty == 1'b1 && full == 1'b0)
            $display("TEST 1: Reset - PASS");
        else begin
            $display("TEST 1: Reset - FAIL");
            all_pass = 1'b0;
        end


        // TEST 2: WRITE ONE VALUE

        wr_en = 1;
        d_in = 16'h0010;

        #10;

        wr_en = 0;

        if (empty == 1'b0)
            $display("TEST 2: Write one value - PASS");
        else begin
            $display("TEST 2: Write one value - FAIL");
            all_pass = 1'b0;
        end


        // TEST 3: READ ONE VALUE

        rd_en = 1;

        #10;

        rd_en = 0;

        if (d_out == 16'h0010 && empty == 1'b1)
            $display("TEST 3: Read one value - PASS");
        else begin
            $display("TEST 3: Read one value - FAIL");
            all_pass = 1'b0;
        end


        // TEST 4: WRITE MULTIPLE VALUES

        wr_en = 1;

        d_in = 16'h0001;
        #10;

        d_in = 16'h0002;
        #10;

        d_in = 16'h0003;
        #10;

        d_in = 16'h0004;
        #10;

        wr_en = 0;

        if (empty == 1'b0)
            $display("TEST 4: Multiple writes - PASS");
        else begin
            $display("TEST 4: Multiple writes - FAIL");
            all_pass = 1'b0;
        end


        // TEST 5: FIFO ORDER

        test_pass = 1'b1;

        rd_en = 1;

        #10;
        if (d_out != 16'h0001)
            test_pass = 1'b0;

        #10;
        if (d_out != 16'h0002)
            test_pass = 1'b0;

        #10;
        if (d_out != 16'h0003)
            test_pass = 1'b0;

        #10;
        if (d_out != 16'h0004)
            test_pass = 1'b0;

        rd_en = 0;

        if (test_pass)
            $display("TEST 5: FIFO order - PASS");
        else begin
            $display("TEST 5: FIFO order - FAIL");
            all_pass = 1'b0;
        end


        // TEST 6: FILL FIFO

        wr_en = 1;

        d_in = 16'h0001;
        #10;

        d_in = 16'h0002;
        #10;

        d_in = 16'h0003;
        #10;

        d_in = 16'h0004;
        #10;

        d_in = 16'h0005;
        #10;

        d_in = 16'h0006;
        #10;

        d_in = 16'h0007;
        #10;

        d_in = 16'h0008;
        #10;

        wr_en = 0;

        if (full == 1'b1 && empty == 1'b0)
            $display("TEST 6: Fill FIFO - PASS");
        else begin
            $display("TEST 6: Fill FIFO - FAIL");
            all_pass = 1'b0;
        end


        // TEST 7: WRITE WHEN FULL

        wr_en = 1;
        d_in = 16'h1234;

        #10;

        wr_en = 0;

        if (full == 1'b1)
            $display("TEST 7: Write when full - PASS");
        else begin
            $display("TEST 7: Write when full - FAIL");
            all_pass = 1'b0;
        end


        // TEST 8: READ FROM FULL FIFO

        rd_en = 1;

        #10;

        if (d_out == 16'h0001 && full == 1'b0)
            $display("TEST 8: Read from full FIFO - PASS");
        else begin
            $display("TEST 8: Read from full FIFO - FAIL");
            all_pass = 1'b0;
        end

        rd_en = 0;


        // TEST 9: READ UNTIL EMPTY

        test_pass = 1'b1;

        rd_en = 1;

        #10;
        if (d_out != 16'h0002)
            test_pass = 1'b0;

        #10;
        if (d_out != 16'h0003)
            test_pass = 1'b0;

        #10;
        if (d_out != 16'h0004)
            test_pass = 1'b0;

        #10;
        if (d_out != 16'h0005)
            test_pass = 1'b0;

        #10;
        if (d_out != 16'h0006)
            test_pass = 1'b0;

        #10;
        if (d_out != 16'h0007)
            test_pass = 1'b0;

        #10;
        if (d_out != 16'h0008)
            test_pass = 1'b0;

        rd_en = 0;

        if (empty != 1'b1)
            test_pass = 1'b0;

        if (test_pass)
            $display("TEST 9: Read until empty - PASS");
        else begin
            $display("TEST 9: Read until empty - FAIL");
            all_pass = 1'b0;
        end


        // TEST 10: READ WHEN EMPTY

        rd_en = 1;

        #10;

        rd_en = 0;

        if (empty == 1'b1)
            $display("TEST 10: Read when empty - PASS");
        else begin
            $display("TEST 10: Read when empty - FAIL");
            all_pass = 1'b0;
        end


        // TEST 11: SIMULTANEOUS READ + WRITE

        wr_en = 1;
        d_in = 16'h0010;

        #10;

        wr_en = 0;

        #10;

        wr_en = 1;
        rd_en = 1;
        d_in = 16'h0020;

        #10;

        if (d_out == 16'h0010)
            $display("TEST 11: Simultaneous read/write - PASS");
        else begin
            $display("TEST 11: Simultaneous read/write - FAIL");
            all_pass = 1'b0;
        end

        wr_en = 0;
        rd_en = 0;


        // TEST 12: RESET WHILE FIFO HAS DATA

        wr_en = 1;
        d_in = 16'h1234;

        #10;

        wr_en = 0;

        rst_n = 0;

        #10;

        rst_n = 1;

        #10;

        if (empty == 1'b1 && full == 1'b0)
            $display("TEST 12: Reset with data - PASS");
        else begin
            $display("TEST 12: Reset with data - FAIL");
            all_pass = 1'b0;
        end


        // FINAL RESULT

        #10;

        if (all_pass == 1'b1)
            $display("ALL TESTS PASSED");
        else
            $display("SOME TESTS FAILED");

        $finish;

    end

endmodule

fifo_sync.vcd
$date
	Sat Aug 15 22:05:28 2026
$end
$version
	Icarus Verilog
$end
$timescale
	1ps
$end
$scope module fifo_sync_tb $end
$var wire 1 ! full $end
$var wire 1 " empty $end
$var wire 16 # d_out [15:0] $end
$var parameter 32 $ data_width $end
$var parameter 32 % fifo_depth $end
$var reg 1 & all_pass $end
$var reg 1 ' clk $end
$var reg 1 ( cs $end
$var reg 16 ) d_in [15:0] $end
$var reg 1 * rd_en $end
$var reg 1 + rst_n $end
$var reg 1 , test_pass $end
$var reg 1 - wr_en $end
$scope module dut $end
$var wire 1 ' clk $end
$var wire 1 ( cs $end
$var wire 16 . d_in [15:0] $end
$var wire 1 * rd_en $end
$var wire 1 + rst_n $end
$var wire 1 - wr_en $end
$var wire 1 ! full $end
$var wire 1 " empty $end
$var parameter 32 / data_width $end
$var parameter 32 0 fifo_depth $end
$var parameter 32 1 pointer_width $end
$var reg 16 2 d_out [15:0] $end
$var reg 4 3 rd_ptr [3:0] $end
$var reg 4 4 wr_ptr [3:0] $end
$upscope $end
$upscope $end
$enddefinitions $end
$comment Show the parameter values. $end
$dumpall
b11 1
b1000 0
b10000 /
b1000 %
b10000 $
$end
#0
$dumpvars
b0 4
b0 3
bx 2
b0 .
0-
1,
0+
0*
b0 )
0(
0'
1&
bx #
1"
0!
$end
#5000
1'
#10000
0'
#12000
1(
1+
#15000
1'
#20000
0'
#22000
b10000 )
b10000 .
1-
#25000
0"
b1 4
1'
#30000
0'
#32000
1*
0-
#35000
1"
b1 3
b10000 #
b10000 2
1'
#40000
0'
#42000
b1 )
b1 .
1-
0*
#45000
0"
b10 4
1'
#50000
0'
#52000
b10 )
b10 .
#55000
b11 4
1'
#60000
0'
#62000
b11 )
b11 .
#65000
b100 4
1'
#70000
0'
#72000
b100 )
b100 .
#75000
b101 4
1'
#80000
0'
#82000
1*
0-
#85000
b10 3
b1 #
b1 2
1'
#90000
0'
#95000
b11 3
b10 #
b10 2
1'
#100000
0'
#105000
b100 3
b11 #
b11 2
1'
#110000
0'
#115000
1"
b101 3
b100 #
b100 2
1'
#120000
0'
#122000
b1 )
b1 .
1-
0*
#125000
0"
b110 4
1'
#130000
0'
#132000
b10 )
b10 .
#135000
b111 4
1'
#140000
0'
#142000
b11 )
b11 .
#145000
b1000 4
1'
#150000
0'
#152000
b100 )
b100 .
#155000
b1001 4
1'
#160000
0'
#162000
b101 )
b101 .
#165000
b1010 4
1'
#170000
0'
#172000
b110 )
b110 .
#175000
b1011 4
1'
#180000
0'
#182000
b111 )
b111 .
#185000
b1100 4
1'
#190000
0'
#192000
b1000 )
b1000 .
#195000
1!
b1101 4
1'
#200000
0'
#202000
b1001000110100 )
b1001000110100 .
1-
#205000
1'
#210000
0'
#212000
1*
0-
#215000
0!
b110 3
b1 #
b1 2
1'
#220000
0'
#222000
1*
#225000
b111 3
b10 #
b10 2
1'
#230000
0'
#235000
b1000 3
b11 #
b11 2
1'
#240000
0'
#245000
b1001 3
b100 #
b100 2
1'
#250000
0'
#255000
b1010 3
b101 #
b101 2
1'
#260000
0'
#265000
b1011 3
b110 #
b110 2
1'
#270000
0'
#275000
b1100 3
b111 #
b111 2
1'
#280000
0'
#285000
1"
b1101 3
b1000 #
b1000 2
1'
#290000
0'
#292000
1*
#295000
1'
#300000
0'
#302000
b10000 )
b10000 .
1-
0*
#305000
0"
b1110 4
1'
#310000
0'
#312000
0-
#315000
1'
#320000
0'
#322000
b100000 )
b100000 .
1*
1-
#325000
b1110 3
b10000 #
b10000 2
b1111 4
1'
#330000
0'
#332000
b1001000110100 )
b1001000110100 .
0*
1-
#335000
b0 4
1'
#340000
0'
#342000
0!
1"
b0 3
0+
0-
#345000
1'
#350000
0'
#352000
1+
